[
    {
        "idx": 1,
        "filter_id": "near",
        "img_src": "cafe1",
        "name": "카페 저기",
        "location": "서울시 마포구 와우산로 123456",
        "type": ["조용한", "힙한"],
        "remain_seats": 2,
        "total_seats": 10,
        "time": "10:00 ~ 22:00",
        "call": "010-1234-4567",
        "menu": {
            "에스프레소": "500원",
            "아메리카노": "1000원",
            "라떼": "2000원",
            "바닐라라떼": "3000원",
            "카페모카": "3000원",
            "카라멜 마끼아또": "3000원"
        }
    },
    {
        "idx": 2,
        "filter_id": "near",
        "img_src": "cafe2",
        "name": "카페 요기",
        "location": "서울시 마포구 와우산로 123456",
        "type": ["테라스", "감성"],
        "remain_seats": 4,
        "total_seats": 16,
        "time": "10:00 ~ 22:00",
        "call": "010-1234-4567",
        "menu": {
            "에스프레소": "500원",
            "아메리카노": "1000원",
            "라떼": "2000원",
            "바닐라라떼": "3000원",
            "카페모카": "3000원",
            "카라멜 마끼아또": "3000원"
        }
    },
    {
        "idx": 3,
        "filter_id": "famous",
        "img_src": "cafe3",
        "name": "카페 쩌기",
        "location": "서울시 마포구 와우산로 123456",
        "type": ["분위기 좋은", "카공"],
        "remain_seats": 3,
        "total_seats": 15,
        "time": "10:00 ~ 22:00",
        "call": "010-1234-4567",
        "menu": {
            "에스프레소": "500원",
            "아메리카노": "1000원",
            "라떼": "2000원",
            "바닐라라떼": "3000원",
            "카페모카": "3000원",
            "카라멜 마끼아또": "3000원"
        }
    },
    {
        "idx": 4,
        "filter_id": "quiet",
        "img_src": "cafe4",
        "name": "카페 여기",
        "location": "서울시 마포구 와우산로 123456",
        "type": ["분위기 좋은", "카공"],
        "remain_seats": 6,
        "total_seats": 18,
        "time": "10:00 ~ 22:00",
        "call": "010-1234-4567",
        "menu": {
            "에스프레소": "500원",
            "아메리카노": "1000원",
            "라떼": "2000원",
            "바닐라라떼": "3000원",
            "카페모카": "3000원",
            "카라멜 마끼아또": "3000원"
        }
    }
]